LICENSE
MANIFEST.in
README.rst
THANKS
changelog.rst
setup.py
tests.py
Momoko.egg-info/PKG-INFO
Momoko.egg-info/SOURCES.txt
Momoko.egg-info/dependency_links.txt
Momoko.egg-info/requires.txt
Momoko.egg-info/top_level.txt
docs/Makefile
docs/api.rst
docs/changelog.rst
docs/conf.py
docs/index.rst
docs/installation.rst
docs/make.bat
docs/tutorial.rst
examples/gen_example.py
momoko/__init__.py
momoko/connection.py
momoko/exceptions.py